qdatalib/__init__.py
qdatalib/_version.py
qdatalib/mongo_conf.py
qdatalib/tolib.py
qdatalib/conf/__init__.py
qdatalib/conf/telemetry.ini
qdatalib/telemetry/__init__.py
qdatalib/telemetry/telemetry_functions.py
qdatalib-0.1.0.dist-info/LICENSE.rst
qdatalib-0.1.0.dist-info/METADATA
qdatalib-0.1.0.dist-info/WHEEL
qdatalib-0.1.0.dist-info/top_level.txt
qdatalib-0.1.0.dist-info/RECORD
