Metadata-Version: 2.1
Name: qdatalib
Version: 0.1.0
Summary: Library for Quantum Data file Organization
Home-page: UNKNOWN
Author: Rasmus Bjerregaard Christensen
Author-email: rbcmail@gmail.com
License: UNKNOWN
Platform: UNKNOWN
Classifier: Development Status :: 2 - Pre-Alpha
Classifier: Intended Audience :: Science/Research
Classifier: Programming Language :: Python :: 3.7
Requires-Python: >=3.7
Requires-Dist: pymongo
Requires-Dist: dnspython
Requires-Dist: qcodes (>=0.25)
